{
  "721": {
    "POLICY_ID_PLACEHOLDER": {
      "FFEC0072": {
        "name": "Eternal Coil #0072",
        "image": "ipfs://IMAGE_CID_PLACEHOLDER/FFEC0072.png",
        "mediaType": "image/png",
        "description": "A prototype Fractal Fuzion Eternal Coil. Planning metadata only; not minted.",
        "files": [
          {
            "name": "Eternal Coil #0072",
            "mediaType": "image/png",
            "src": "ipfs://IMAGE_CID_PLACEHOLDER/FFEC0072.png"
          }
        ],
        "Collection": "Fractal Fuzion Eternal Coil Prototype",
        "Background": "Deep Space Black",
        "Serpent Form": "Spiral Coil",
        "Material": "Cardano Blue Scales",
        "Eyes": "Blue ADA Eyes",
        "Head Trait": "Space Helmet Ring",
        "Aura": "Soft Glow",
        "Cardano Lore": "Epoch",
        "Edition Tier": "Common",
        "Prototype": "true"
      }
    },
    "version": 2
  }
}
